.coveragerc
CHANGES.rst
CONTRIBUTORS.rst
MANIFEST.in
README.rst
buildout.cfg
setup.py
travis.cfg
docs/LICENSE.GPL
docs/LICENSE.rst
docs/index.rst
src/collective/__init__.py
src/collective.relatedslider.egg-info/PKG-INFO
src/collective.relatedslider.egg-info/SOURCES.txt
src/collective.relatedslider.egg-info/dependency_links.txt
src/collective.relatedslider.egg-info/entry_points.txt
src/collective.relatedslider.egg-info/namespace_packages.txt
src/collective.relatedslider.egg-info/not-zip-safe
src/collective.relatedslider.egg-info/requires.txt
src/collective.relatedslider.egg-info/top_level.txt
src/collective/relatedslider/__init__.py
src/collective/relatedslider/behavior.py
src/collective/relatedslider/collective.relatedslider.pot
src/collective/relatedslider/configure.zcml
src/collective/relatedslider/interfaces.py
src/collective/relatedslider/setuphandlers.py
src/collective/relatedslider/testing.py
src/collective/relatedslider/browser/__init__.py
src/collective/relatedslider/browser/configure.zcml
src/collective/relatedslider/browser/relatedslider.pt
src/collective/relatedslider/browser/viewlets.py
src/collective/relatedslider/browser/static/.gitkeep
src/collective/relatedslider/browser/static/relatedslider.css
src/collective/relatedslider/locales/collective.relatedslider.pot
src/collective/relatedslider/locales/update.sh
src/collective/relatedslider/profiles/default/browserlayer.xml
src/collective/relatedslider/profiles/default/collectiverelatedslider_default.txt
src/collective/relatedslider/profiles/default/metadata.xml
src/collective/relatedslider/profiles/default/registry.xml
src/collective/relatedslider/profiles/uninstall/browserlayer.xml
src/collective/relatedslider/profiles/uninstall/collectiverelatedslider_uninstall.txt
src/collective/relatedslider/profiles/uninstall/registry.xml
src/collective/relatedslider/tests/__init__.py
src/collective/relatedslider/tests/test_robot.py
src/collective/relatedslider/tests/test_setup.py
src/collective/relatedslider/tests/robot/test_example.robot