Metadata-Version: 2.1
Name: collective.relatedslider
Version: 0.2
Summary: Plone addon that creates a slider viewlet containing related content.
Home-page: http://pypi.python.org/pypi/collective.relatedslider
Author: Jazkarta, Inc.
Author-email: alecpm@gmail.com
License: GPL version 2
Keywords: Python Plone
Platform: UNKNOWN
Classifier: Environment :: Web Environment
Classifier: Framework :: Plone
Classifier: Framework :: Plone :: 5.0
Classifier: Programming Language :: Python
Classifier: Programming Language :: Python :: 2.7
Classifier: Operating System :: OS Independent
Classifier: License :: OSI Approved :: GNU General Public License v2 (GPLv2)
Provides-Extra: test
